sopel_ai/__init__.py
sopel_ai/config.py
sopel_ai/core.py
sopel_ai/errors.py
sopel_ai/plugin.py
sopel_ai-1.3.7.dist-info/licenses/LICENSE.txt
sopel_ai-1.3.7.dist-info/METADATA
sopel_ai-1.3.7.dist-info/WHEEL
sopel_ai-1.3.7.dist-info/entry_points.txt
sopel_ai-1.3.7.dist-info/top_level.txt
sopel_ai-1.3.7.dist-info/RECORD
