Metadata-Version: 2.4
Name: sopel-ai
Version: 1.3.7
Summary: Sopel AI - an LLM enhanced chat bot plug-in
Author-email: The SopelAI team <sopel_ai@cime.net>
Project-URL: Homepage, https://github.com/pr3d4t0r/sopel_ai
Project-URL: Bug Tracker, https://github.com/pr3d4t0r/sopel_ai/issues
Keywords: ai,bot,irc,llm,plugin,sopel
Classifier: Intended Audience :: Developers
Classifier: Intended Audience :: System Administrators
Classifier: Operating System :: MacOS
Classifier: Operating System :: POSIX :: Linux
Classifier: Operating System :: Unix
Classifier: Programming Language :: Python :: 3
Classifier: Programming Language :: Python :: 3.9
Classifier: Topic :: Communications :: Chat
Classifier: Topic :: Utilities
Requires-Python: >=3.9
License-File: LICENSE.txt
Requires-Dist: perplexipy==1.3.1
Requires-Dist: sopel>=7.1
Requires-Dist: tinydb
Dynamic: license-file
